attentive/__init__.py
attentive/attentive.py
attentive/quit.py
attentive-0.1.5.dist-info/DESCRIPTION.rst
attentive-0.1.5.dist-info/METADATA
attentive-0.1.5.dist-info/RECORD
attentive-0.1.5.dist-info/WHEEL
attentive-0.1.5.dist-info/metadata.json
attentive-0.1.5.dist-info/top_level.txt
